sky130/__init__.py
sky130/components.py
sky130/config.py
sky130/layers.py
sky130/nmos.py
sky130/spice_models.py
sky130/tech.py
sky130/circuits/sample.pic.yml
sky130/gds/sky130_fd_sc_hd__a2111o_1.gds
sky130/gds/sky130_fd_sc_hd__a2111o_2.gds
sky130/gds/sky130_fd_sc_hd__a2111o_4.gds
sky130/gds/sky130_fd_sc_hd__a2111oi_0.gds
sky130/gds/sky130_fd_sc_hd__a2111oi_1.gds
sky130/gds/sky130_fd_sc_hd__a2111oi_2.gds
sky130/gds/sky130_fd_sc_hd__a2111oi_4.gds
sky130/gds/sky130_fd_sc_hd__a211o_1.gds
sky130/gds/sky130_fd_sc_hd__a211o_2.gds
sky130/gds/sky130_fd_sc_hd__a211o_4.gds
sky130/gds/sky130_fd_sc_hd__a211oi_1.gds
sky130/gds/sky130_fd_sc_hd__a211oi_2.gds
sky130/gds/sky130_fd_sc_hd__a211oi_4.gds
sky130/gds/sky130_fd_sc_hd__a21bo_1.gds
sky130/gds/sky130_fd_sc_hd__a21bo_2.gds
sky130/gds/sky130_fd_sc_hd__a21bo_4.gds
sky130/gds/sky130_fd_sc_hd__a21boi_0.gds
sky130/gds/sky130_fd_sc_hd__a21boi_1.gds
sky130/gds/sky130_fd_sc_hd__a21boi_2.gds
sky130/gds/sky130_fd_sc_hd__a21boi_4.gds
sky130/gds/sky130_fd_sc_hd__a21o_1.gds
sky130/gds/sky130_fd_sc_hd__a21o_2.gds
sky130/gds/sky130_fd_sc_hd__a21o_4.gds
sky130/gds/sky130_fd_sc_hd__a21oi_1.gds
sky130/gds/sky130_fd_sc_hd__a21oi_2.gds
sky130/gds/sky130_fd_sc_hd__a21oi_4.gds
sky130/gds/sky130_fd_sc_hd__a221o_1.gds
sky130/gds/sky130_fd_sc_hd__a221o_2.gds
sky130/gds/sky130_fd_sc_hd__a221o_4.gds
sky130/gds/sky130_fd_sc_hd__a221oi_1.gds
sky130/gds/sky130_fd_sc_hd__a221oi_2.gds
sky130/gds/sky130_fd_sc_hd__a221oi_4.gds
sky130/gds/sky130_fd_sc_hd__a222oi_1.gds
sky130/gds/sky130_fd_sc_hd__a22o_1.gds
sky130/gds/sky130_fd_sc_hd__a22o_2.gds
sky130/gds/sky130_fd_sc_hd__a22o_4.gds
sky130/gds/sky130_fd_sc_hd__a22oi_1.gds
sky130/gds/sky130_fd_sc_hd__a22oi_2.gds
sky130/gds/sky130_fd_sc_hd__a22oi_4.gds
sky130/gds/sky130_fd_sc_hd__a2bb2o_1.gds
sky130/gds/sky130_fd_sc_hd__a2bb2o_2.gds
sky130/gds/sky130_fd_sc_hd__a2bb2o_4.gds
sky130/gds/sky130_fd_sc_hd__a2bb2oi_1.gds
sky130/gds/sky130_fd_sc_hd__a2bb2oi_2.gds
sky130/gds/sky130_fd_sc_hd__a2bb2oi_4.gds
sky130-0.11.1.dist-info/LICENSE
sky130-0.11.1.dist-info/WHEEL
sky130-0.11.1.dist-info/METADATA
sky130-0.11.1.dist-info/RECORD
