Metadata-Version: 2.1
Name: sky130
Version: 0.11.1
Summary: skywater130 pdk
Keywords: python
Author-email: gdsfactory <contact@gdsfactory.com>
Requires-Python: >=3.10
Classifier: License :: OSI Approved :: MIT License
Classifier: Programming Language :: Python :: 3.10
Classifier: Programming Language :: Python :: 3.11
Classifier: Operating System :: OS Independent
Requires-Dist: gdsfactory~=7.26.1
Requires-Dist: PySpice
Requires-Dist: pytest ; extra == "dev"
Requires-Dist: pytest-cov ; extra == "dev"
Requires-Dist: pytest_regressions ; extra == "dev"
Requires-Dist: pre-commit ; extra == "dev"
Requires-Dist: jupytext ; extra == "docs"
Requires-Dist: jupyter-book==1.0.0 ; extra == "docs"
Provides-Extra: dev
Provides-Extra: docs
